process_includes.py
generateDS-2.44.3.data/scripts/gds_collect_namespace_mappings.py
generateDS-2.44.3.data/scripts/gends_extract_simple_types.py
generateDS-2.44.3.data/scripts/gends_generate_django.py
generateDS-2.44.3.data/scripts/gends_run_gen_django.py
generateDS-2.44.3.data/scripts/generateDS.py
generateDS-2.44.3.data/scripts/generateds_gui.py
generateDS-2.44.3.data/scripts/process_includes.py
libgenerateDS/__init__.py
libgenerateDS/process_includes.py
libgenerateDS/gui/__init__.py
libgenerateDS/gui/generateds_gui.py
libgenerateDS/gui/generateds_gui_session.py
generateDS-2.44.3.dist-info/LICENSE
generateDS-2.44.3.dist-info/METADATA
generateDS-2.44.3.dist-info/WHEEL
generateDS-2.44.3.dist-info/entry_points.txt
generateDS-2.44.3.dist-info/top_level.txt
generateDS-2.44.3.dist-info/RECORD
