Metadata-Version: 2.1
Name: generateDS
Version: 2.44.3
Summary: Generate Python data structures and XML parser from Xschema
Home-page: http://www.davekuhlman.org/generateDS.html
Author: Dave Kuhlman
Author-email: dkuhlman@davekuhlman.org
Maintainer: Dave Kuhlman
Maintainer-email: dkuhlman@davekuhlman.org
License: http://www.opensource.org/licenses/mit-license.php
Platform: platform-independent
Classifier: Programming Language :: Python :: 2
Classifier: Programming Language :: Python :: 3
Classifier: License :: OSI Approved :: MIT License
Classifier: Operating System :: OS Independent
License-File: LICENSE
Requires-Dist: six
Requires-Dist: lxml
Requires-Dist: requests >=2.21.0
